prefect_stitch/__init__.py
prefect_stitch/_version.py
prefect_stitch/credentials.py
prefect_stitch/exceptions.py
prefect_stitch/stitch_client.py
prefect_stitch/tasks.py
prefect_stitch-0.1.4.dist-info/LICENSE
prefect_stitch-0.1.4.dist-info/METADATA
prefect_stitch-0.1.4.dist-info/WHEEL
prefect_stitch-0.1.4.dist-info/top_level.txt
prefect_stitch-0.1.4.dist-info/RECORD
